[
  {
    "name": "Voyage3",
    "description": "Submission for I Love Hackathon: Pune Web3 Edition",
    "html_url": "https://github.com/altf4-games/Voyage3",
    "language": "JavaScript",
    "stargazers_count": 0,
    "forks_count": 0,
    "updated_at": "2025-08-28T15:24:54Z",
    "fork": false,
    "homepage": "https://voyage3.vercel.app"
  },
  {
    "name": "RunFT",
    "description": "Eth Delhi Submission",
    "html_url": "https://github.com/altf4-games/RunFT",
    "language": "TypeScript",
    "stargazers_count": 0,
    "forks_count": 2,
    "updated_at": "2025-10-25T10:26:33Z",
    "fork": false,
    "homepage": "https://runft.vercel.app"
  },
  {
    "name": "Cultur.AI",
    "description": "Submission for Mumbai Hacks",
    "html_url": "https://github.com/altf4-games/Cultur.AI",
    "language": "JavaScript",
    "stargazers_count": 0,
    "forks_count": 0,
    "updated_at": "2025-08-28T15:24:25Z",
    "fork": false,
    "homepage": "https://culturai.vercel.app"
  },
  {
    "name": "CatchPhish",
    "description": "Repository for IDEA Hackathon submission by Team Phish and Chips",
    "html_url": "https://github.com/altf4-games/CatchPhish",
    "language": "Jupyter Notebook",
    "stargazers_count": 0,
    "forks_count": 0,
    "updated_at": "2025-03-29T12:02:32Z",
    "fork": false,
    "homepage": "https://catchphish.vercel.app"
  },
  {
    "name": "Heart-Quake",
    "description": "Retro FPS for Winter Melon Game-Jam",
    "html_url": "https://github.com/altf4-games/Heart-Quake",
    "language": "C#",
    "stargazers_count": 0,
    "forks_count": 0,
    "updated_at": "2024-07-27T05:28:09Z",
    "fork": false,
    "homepage": ""
  },
  {
    "name": "Accident-Analysis-Dashboard",
    "description": "Repository for Accident Analysis Dashboard",
    "html_url": "https://github.com/altf4-games/Accident-Analysis-Dashboard",
    "language": "CSS",
    "stargazers_count": 0,
    "forks_count": 1,
    "updated_at": "2025-05-11T07:54:02Z",
    "fork": false,
    "homepage": "https://ksp-da-dashboard.vercel.app"
  }
]
